{
  "schema_version": "1.0",
  "apm_queries": {
    "app_500_errors": {
      "description": "Application Services - HTTP 500 errors",
      "query": "service:(my-app-web OR my-worker-sql OR my-worker-http) env:qa-west @http.status_code:500"
    },
    "app_all_errors": {
      "description": "Application Services - All errors",
      "query": "service:(my-app-web OR my-worker-sql OR my-worker-http) env:qa-west status:error"
    },
    "app_slow_requests": {
      "description": "Application Services - Slow requests (>5s)",
      "query": "service:(my-app-web OR my-worker-sql OR my-worker-http) env:qa-west @duration:>5000000000"
    }
  },

  "log_queries": {
    "app_error_logs": {
      "description": "Application Services - Application error logs",
      "query": "service:my-app-web status:error"
    },
    "app_exception_logs": {
      "description": "Application Services - Logs with stack traces",
      "query": "service:my-app-web \"Exception\""
    }
  }
}
